tutorial/__init__.py
tutorial/items.py
tutorial/middlewares.py
tutorial/pipelines.py
tutorial/settings.py
tutorial/spiders/__init__.py
tutorial/spiders/quotes_spider.py
iipg-0.0.1.dist-info/METADATA
iipg-0.0.1.dist-info/WHEEL
iipg-0.0.1.dist-info/top_level.txt
iipg-0.0.1.dist-info/RECORD
